{
  "version": "7",
  "dialect": "postgresql",
  "entries": [
    {
      "idx": 0,
      "version": "7",
      "when": 1745009677885,
      "tag": "0000_minor_hex",
      "breakpoints": true
    },
    {
      "idx": 1,
      "version": "7",
      "when": 1745361096008,
      "tag": "0001_slimy_leo",
      "breakpoints": true
    },
    {
      "idx": 2,
      "version": "7",
      "when": 1745361141897,
      "tag": "0002_spicy_rick_jones",
      "breakpoints": true
    },
    {
      "idx": 3,
      "version": "7",
      "when": 1745361251029,
      "tag": "0003_brainy_zarda",
      "breakpoints": true
    },
    {
      "idx": 4,
      "version": "7",
      "when": 1746400647909,
      "tag": "0004_shallow_invisible_woman",
      "breakpoints": true
    },
    {
      "idx": 5,
      "version": "7",
      "when": 1746409094858,
      "tag": "0005_gifted_blockbuster",
      "breakpoints": true
    },
    {
      "idx": 6,
      "version": "7",
      "when": 1746453108016,
      "tag": "0006_short_stellaris",
      "breakpoints": true
    },
    {
      "idx": 7,
      "version": "7",
      "when": 1746478910268,
      "tag": "0007_strong_colonel_america",
      "breakpoints": true
    },
    {
      "idx": 8,
      "version": "7",
      "when": 1746480070516,
      "tag": "0008_easy_nitro",
      "breakpoints": true
    },
    {
      "idx": 9,
      "version": "7",
      "when": 1746480481872,
      "tag": "0009_exotic_forge",
      "breakpoints": true
    }
  ]
}